spamsum.so
pyspamsum-1.0.7.dist-info/LICENSE
pyspamsum-1.0.7.dist-info/METADATA
pyspamsum-1.0.7.dist-info/WHEEL
pyspamsum-1.0.7.dist-info/top_level.txt
pyspamsum-1.0.7.dist-info/RECORD
