Metadata-Version: 2.2
Name: pyspamsum
Version: 1.0.7
Summary: A Python wrapper for Andrew Tridgell's spamsum algorithm
Author-email: Russell Keith-Magee <russell@keith-magee.com>
Maintainer-email: Russell Keith-Magee <russell@keith-magee.com>
License: New BSD
Project-URL: Homepage, https://github.com/freakboy3742/pyspamsum/
Project-URL: Tracker, https://github.com/freakboy3742/pyspamsum/issues
Project-URL: Source, https://github.com/freakboy3742/pyspamsum/
Keywords: spamsum
Classifier: Development Status :: 5 - Production/Stable
Classifier: License :: OSI Approved :: BSD License
Classifier: Operating System :: OS Independent
Classifier: Programming Language :: Python :: 3
Classifier: Programming Language :: Python :: 3.9
Classifier: Programming Language :: Python :: 3.10
Classifier: Programming Language :: Python :: 3.11
Classifier: Programming Language :: Python :: 3.12
Classifier: Programming Language :: Python :: 3.13
Classifier: Topic :: Text Processing
Classifier: Topic :: Utilities
Requires-Python: >=3.9
License-File: LICENSE
Provides-Extra: test
Requires-Dist: pytest==8.3.4; extra == "test"
Provides-Extra: dev
Requires-Dist: pre-commit==4.1.0; extra == "dev"
Requires-Dist: ruff==0.9.6; extra == "dev"
Requires-Dist: setuptools_scm==8.1.0; extra == "dev"
Requires-Dist: tox==4.24.1; extra == "dev"
Download-URL: 
